ymtests/qenvpbuf.py
ymtests/qbmixenv.py
ymtests/qnoispec.py
ymtests/qtonpbuf.py
ymtests/__init__.py
ymtests/dosound2.py
ymtests/qtinheri.py
ymtests/qanlgmix.py
ymtests/dosound1.py
ymtests/qenvrbuf.py
ymtests/qmnreset.py
ymtests/mkdsd.py
ymtests/qenvpzer.py
ymtests/dosound0.py
ymtests/qtonpzer.py
ymtests/qtonflip.py
ymtests/qmtreset.py
ymtests/qnoipbuf.py
pym2149/const.py
pym2149/buf.py
pym2149/lha.py
pym2149/txt.py
pym2149/budgie.py
pym2149/clock.py
pym2149/ym2149.py
pym2149/osc2.py
pym2149/pitch.py
pym2149/dosound.py
pym2149/timer.py
pym2149/wav.py
pym2149/config.py
pym2149/mix.py
pym2149/timerimpl.py
pym2149/lfsr.py
pym2149/txt.arid
pym2149/lurlene.py
pym2149/__init__.py
pym2149/mfp.py
pym2149/vis.py
pym2149/power.py
pym2149/reg.py
pym2149/resid.py
pym2149/ymplayer.py
pym2149/out.py
pym2149/dac.py
pym2149/shapes.py
pym2149/warmup.py
pym2149/minblep.py
pym2149/util.py
pym2149/iface.py
pym2149/dsd.arid
pym2149/nod.py
pym2149/ymformat.py
pym2149/root.arid
pym2149/osc2_turbo/rtoneimpl.cpython-39-x86_64-linux-gnu.so
pym2149/osc2_turbo/shapeimpl.pyxbld
pym2149/osc2_turbo/shapeimpl.cpython-39-x86_64-linux-gnu.so
pym2149/osc2_turbo/__init__.py
pym2149/osc2_turbo/rtoneimpl.pyxbld
pym2149/osc2_turbo/shapeimpl.pyx
pym2149/osc2_turbo/rtoneimpl.pyx
pym2149/native/calsa.cpython-39-x86_64-linux-gnu.so
pym2149/native/ctime.pxd
pym2149/native/resid.cpython-39-x86_64-linux-gnu.so
pym2149/native/resid.pyxbld
pym2149/native/__init__.py
pym2149/native/resid.pyx
pym2149/native/calsa.pyxbld
pym2149/native/calsa.pyx
pym2149/scripts/lc2jack.py
pym2149/scripts/ym2jack.py
pym2149/scripts/dosound2txt.py
pym2149/scripts/lc2wav.py
pym2149/scripts/__init__.py
pym2149/scripts/dosound2wav.py
pym2149/scripts/ym2portaudio.py
pym2149/scripts/ym2wav.py
pym2149/scripts/lc2txt.py
pym2149/scripts/dsd2wav.py
pym2149/scripts/ym2txt.py
pym2149/scripts/lc2portaudio.py
pym2149/scripts/bpmtool.py
pym2149-39.dist-info/RECORD
pym2149-39.dist-info/WHEEL
pym2149-39.dist-info/top_level.txt
pym2149-39.dist-info/METADATA
pym2149-39.dist-info/entry_points.txt
pym2149-39.dist-info/licenses/COPYING
