Metadata-Version: 2.1
Name: pym2149
Version: 39
Summary: YM2149 emulator supporting YM files, OSC to JACK, PortAudio, WAV
Home-page: https://github.com/combatopera/pym2149
Author: Andrzej Cichocki
Author-email: 3613868+combatopera@users.noreply.github.com
License-File: COPYING
Requires-Dist: aridity>=84
Requires-Dist: diapyr>=26
Requires-Dist: foyndation>=15
Requires-Dist: lagoon>=49
Requires-Dist: Lurlene>=13
Requires-Dist: minBlepy>=16
Requires-Dist: numpy>=2.0.2
Requires-Dist: outjack>=15
Requires-Dist: pyrbo>=18
Requires-Dist: splut>=4
Requires-Dist: timelyOSC>=4
